npdatetime/__init__.py
npdatetime/__init__.pyi
npdatetime/_custom_strptime.py
npdatetime/config.py
npdatetime/utils.py
npdatetime/data/calendar_bs.csv
npdatetime-0.1.2.post2.dist-info/LICENSE
npdatetime-0.1.2.post2.dist-info/METADATA
npdatetime-0.1.2.post2.dist-info/WHEEL
npdatetime-0.1.2.post2.dist-info/top_level.txt
npdatetime-0.1.2.post2.dist-info/RECORD
