Metadata-Version: 2.1
Name: npdatetime
Version: 0.1.2.post2
Summary: A Python package that provides advanced functionality for handling Nepali dates and times, including support for the Bikram Sambat calendar system and Nepal Time (NPT). Ideal for developers working with Nepali date-related applications, offering seamless conversion, manipulation, and formatting of dates and times in the Nepali calendar.
Home-page: https://github.com/4mritGiri/npdatetime
Author: Amrit Giri
Author-email: Amrit Giri <amritgiri02595@gmail.com>
License: The MIT License (MIT)
Project-URL: Homepage, https://github.com/4mritGiri/npdatetime#readme
Project-URL: Issues, https://github.com/4mritGiri/npdatetime/issues
Keywords: Nepali Date,Date Conversion,Datetime,Bikram Sambat,Bikram Samvat,nepali,B.S.,BS,bs,b.s,date,NpDateTime,datetime,time,timezone,nepal,bikram,sambat,samvat,nepali-date,nepali-datetime,nepal-time,npt,nepal-timezone,npdatetime,npdt
Classifier: Programming Language :: Python :: 3
Classifier: License :: OSI Approved :: MIT License
Classifier: Operating System :: OS Independent
Requires-Python: >=3.5
License-File: LICENSE
